lazyenv/__init__.py
lazyenv/cli.py
lazyenv/env.py
lazyenv/env.template
lazyenv/main.py
lazyenv-0.1.0.dist-info/METADATA
lazyenv-0.1.0.dist-info/WHEEL
lazyenv-0.1.0.dist-info/entry_points.txt
lazyenv-0.1.0.dist-info/licenses/LICENSE
lazyenv-0.1.0.dist-info/RECORD
