Metadata-Version: 2.4
Name: lazyenv
Version: 0.1.0
Summary: A Python library for easier management of environment variables.
Author: Valmont
License: MIT License
License-File: LICENSE
Classifier: Development Status :: 3 - Alpha
Classifier: License :: OSI Approved :: MIT License
Classifier: Operating System :: OS Independent
Classifier: Programming Language :: Python :: 3.8
Requires-Python: >=3.8
Requires-Dist: click>=8.1.8
Requires-Dist: python-dotenv>=1.0.1
